{"name":"flare","children":[{"name": "\u6211\u5011", "size": 780}, {"name": "\u9019\u500b", "size": 624}, {"name": "\u4e16\u754c", "size": 157}, {"name": "\u81f3\u65bc", "size": 158}, {"name": "\u9019\u4e9b", "size": 377}, {"name": "\u5e0c\u671b", "size": 292}, {"name": "\u5927\u5bb6", "size": 740}, {"name": "\u770b\u5230", "size": 530}, {"name": "\u6307\u51fa", "size": 129}, {"name": "\u6839\u672c", "size": 290}, {"name": "\u6709\u6c92\u6709", "size": 575}, {"name": "\u5404\u4f4d", "size": 185}, {"name": "\u9019\u7a2e", "size": 408}, {"name": "\u771f\u7684", "size": 710}, {"name": "\u5176\u4ed6", "size": 318}, {"name": "\u5176\u4e2d", "size": 125}, {"name": "\u900f\u904e", "size": 109}, {"name": "\u4e0d\u904e", "size": 578}, {"name": "\u4e0d\u932f", "size": 112}, {"name": "\u5927\u6a13", "size": 111}, {"name": "\u591a\u5c11", "size": 123}, {"name": "\u6700\u5f8c", "size": 365}, {"name": "\u5927\u6982", "size": 215}, {"name": "\u96c6\u5718", "size": 102}, {"name": "\u670b\u53cb", "size": 392}, {"name": "\u7684\u8a71", "size": 274}, {"name": "\u5176\u5be6", "size": 399}, {"name": "\u9019\u6b21", "size": 165}, {"name": "\u9019\u6a23", "size": 665}, {"name": "\u4e0d\u80fd", "size": 266}, {"name": "\u81f3\u5c11", "size": 126}, {"name": "\u770b\u770b", "size": 120}, {"name": "\u570b\u969b", "size": 110}, {"name": "\u771f\u6b63", "size": 102}, {"name": "\u53ef\u80fd", "size": 508}, {"name": "\u611f\u89ba", "size": 227}, {"name": "\u91cd\u8981", "size": 154}, {"name": "\u5099\u8a3b", "size": 170}, {"name": "\u53e6\u5916", "size": 195}, {"name": "\u53f0\u4e2d", "size": 110}, {"name": "\u82f1\u6587", "size": 117}, {"name": "\u554f\u984c", "size": 496}, {"name": "\u4f7f\u7528", "size": 200}, {"name": "\u5b8c\u5168", "size": 171}, {"name": "\u807d\u8aaa", "size": 144}, {"name": "\u9020\u6210", "size": 156}, {"name": "\u4e2d\u5fc3", "size": 129}, {"name": "\u8acb\u554f", "size": 162}, {"name": "\u9032\u5165", "size": 113}, {"name": "\u5718\u9ad4", "size": 101}, {"name": "\u53f0\u5927", "size": 105}, {"name": "\u4efb\u4f55", "size": 112}, {"name": "\u5a92\u9ad4", "size": 353}, {"name": "\u53bb\u5e74", "size": 173}, {"name": "\u6240\u4ee5", "size": 887}, {"name": "\u7167\u7247", "size": 127}, {"name": "\u4e2d\u570b", "size": 440}, {"name": "\u529b\u91cf", "size": 106}, {"name": "\u53f0\u5357", "size": 200}, {"name": "\u53f0\u5317", "size": 340}, {"name": "\u8a31\u591a", "size": 163}, {"name": "\u61c9\u8a72", "size": 408}, {"name": "\u5230\u5e95", "size": 187}, {"name": "\u5fc5\u9808", "size": 106}, {"name": "\u99ac\u82f1\u4e5d", "size": 103}, {"name": "\u63d0\u4f9b", "size": 130}, {"name": "\u5b78\u751f", "size": 203}, {"name": "\u5de5\u4f5c", "size": 298}, {"name": "\u5c0d\u65bc", "size": 142}, {"name": "\u5c0d\u65b9", "size": 108}, {"name": "\u96fb\u8996", "size": 128}, {"name": "\u65b9\u5f0f", "size": 154}, {"name": "\u751a\u81f3", "size": 205}, {"name": "\u5b8c\u6574", "size": 512}, {"name": "\u5b78\u6821", "size": 196}, {"name": "\u5f88\u591a", "size": 564}, {"name": "\u7bc0\u76ee", "size": 133}, {"name": "\u7279\u5225", "size": 135}, {"name": "\u52a0\u4e0a", "size": 122}, {"name": "\u5730\u65b9", "size": 224}, {"name": "\u6240\u6709", "size": 141}, {"name": "\u767c\u751f", "size": 194}, {"name": "\u5e7e\u4e4e", "size": 153}, {"name": "\u76f4\u63a5", "size": 157}, {"name": "\u9700\u8981", "size": 199}, {"name": "\u800c\u5df2", "size": 131}, {"name": "\u767c\u73fe", "size": 349}, {"name": "\u7b49\u7b49", "size": 104}, {"name": "\u5e7e\u500b", "size": 103}, {"name": "\u8981\u6c42", "size": 172}, {"name": "\u570b\u6c11\u9ee8", "size": 203}, {"name": "\u5927\u5b78", "size": 200}, {"name": "\u7e7c\u7e8c", "size": 158}, {"name": "\u4e8b\u4ef6", "size": 150}, {"name": "\u6216\u662f", "size": 193}, {"name": "\u5730\u9707", "size": 155}, {"name": "\u800c\u4e14", "size": 357}, {"name": "\u767c\u5c55", "size": 124}, {"name": "\u9999\u6e2f", "size": 204}, {"name": "\u8b8a\u6210", "size": 163}, {"name": "\u662f\u4e0d\u662f", "size": 180}, {"name": "\u5152\u5b50", "size": 102}, {"name": "\u4e2d\u83ef\u6c11\u570b", "size": 103}, {"name": "\u7d9c\u5408", "size": 121}, {"name": "\u4e8b\u60c5", "size": 194}, {"name": "\u77e5\u9053", "size": 924}, {"name": "\u8b66\u65b9", "size": 119}, {"name": "\u7b97\u662f", "size": 105}, {"name": "\u5225\u4eba", "size": 155}, {"name": "\u4e0d\u7528", "size": 182}, {"name": "\u4ee5\u4e0b", "size": 118}, {"name": "\u4ee5\u4e0a", "size": 220}, {"name": "\u8d77\u4f86", "size": 186}, {"name": "\u4e0d\u7136", "size": 146}, {"name": "\u7136\u5f8c", "size": 433}, {"name": "\u904a\u6232", "size": 118}, {"name": "\u9019\u9ebc", "size": 250}, {"name": "\u53f0\u5317\u5e02", "size": 120}, {"name": "\u65b0\u805e\u6a19\u984c", "size": 167}, {"name": "\u539f\u56e0", "size": 143}, {"name": "\u5167\u5bb9", "size": 144}, {"name": "\u4ee5\u5f8c", "size": 143}, {"name": "\u5973\u751f", "size": 179}, {"name": "\u4e0d\u6703", "size": 512}, {"name": "\u597d\u50cf", "size": 312}, {"name": "\u5982\u679c", "size": 579}, {"name": "\u4e0d\u662f", "size": 912}, {"name": "\u5927\u9678", "size": 210}, {"name": "\u516b\u5366", "size": 823}, {"name": "\u5c0f\u59d0", "size": 107}, {"name": "\u5c0f\u5b69", "size": 108}, {"name": "\u53ef\u662f", "size": 269}, {"name": "\u4ee5\u53ca", "size": 177}, {"name": "\u4ee5\u524d", "size": 242}, {"name": "\u5c0f\u5f1f", "size": 109}, {"name": "\u516c\u53f8", "size": 337}, {"name": "\u793e\u6703", "size": 219}, {"name": "\u7121\u6cd5", "size": 185}, {"name": "\u570b\u4eba", "size": 154}, {"name": "\u4e0d\u540c", "size": 133}, {"name": "\u4ec0\u9ebc", "size": 945}, {"name": "\u7d50\u679c", "size": 321}, {"name": "\u4f60\u5011", "size": 173}, {"name": "\u5c0f\u6642", "size": 113}, {"name": "\u4e0d\u5230", "size": 177}, {"name": "\u6c11\u9032\u9ee8", "size": 146}, {"name": "\u4e0d\u5c11", "size": 175}, {"name": "\u751a\u9ebc", "size": 112}, {"name": "\u5167\u6587", "size": 169}, {"name": "\u73fe\u5834", "size": 197}, {"name": "\u570b\u5bb6", "size": 238}, {"name": "\u53ef\u4ee5", "size": 1230}, {"name": "\u8fa6\u6cd5", "size": 135}, {"name": "\u8a0e\u8ad6", "size": 161}, {"name": "\u539f\u672c", "size": 129}, {"name": "\u6700\u8fd1", "size": 179}, {"name": "\u5982\u4f55", "size": 119}, {"name": "\u60c5\u6cc1", "size": 120}, {"name": "\u73fe\u5728", "size": 759}, {"name": "\u5831\u5c0e", "size": 388}, {"name": "\u4e00\u6a23", "size": 409}, {"name": "\u76ee\u524d", "size": 266}, {"name": "\u4e00\u6b21", "size": 228}, {"name": "\u95dc\u4fc2", "size": 153}, {"name": "\u8a8d\u8b58", "size": 140}, {"name": "\u5e74\u524d", "size": 155}, {"name": "\u6587\u7ae0", "size": 229}, {"name": "\u90a3\u500b", "size": 269}, {"name": "\u904e\u53bb", "size": 157}, {"name": "\u525b\u525b", "size": 111}, {"name": "\u4e00\u7a2e", "size": 130}, {"name": "\u53ea\u6709", "size": 306}, {"name": "\u8001\u95c6", "size": 101}, {"name": "\u53ea\u662f", "size": 414}, {"name": "\u51fa\u73fe", "size": 122}, {"name": "\u500b\u4eba", "size": 362}, {"name": "\u65b0\u805e", "size": 696}, {"name": "\u90a3\u4e9b", "size": 169}, {"name": "\u8cc7\u6599", "size": 135}, {"name": "\u4e00\u76f4", "size": 296}, {"name": "\u6709\u4e9b", "size": 157}, {"name": "\u6709\u4eba", "size": 379}, {"name": "\u96fb\u5f71", "size": 168}, {"name": "\u91ab\u9662", "size": 113}, {"name": "\u624d\u80fd", "size": 106}, {"name": "\u90e8\u5206", "size": 109}, {"name": "\u4e00\u4e0b", "size": 360}, {"name": "\u4e00\u4e9b", "size": 250}, {"name": "\u7814\u7a76", "size": 103}, {"name": "\u4e00\u4f4d", "size": 126}, {"name": "\u904e\u7a0b", "size": 103}, {"name": "\u7f8e\u570b", "size": 294}, {"name": "\u51fa\u4f86", "size": 372}, {"name": "\u4e00\u5b9a", "size": 177}, {"name": "\u9664\u4e86", "size": 194}, {"name": "\u6642\u9593", "size": 295}, {"name": "\u4e00\u5806", "size": 247}, {"name": "\u4e00\u5929", "size": 122}, {"name": "\u4e00\u5e74", "size": 103}, {"name": "\u4f46\u662f", "size": 588}, {"name": "\u559c\u6b61", "size": 257}, {"name": "\u652f\u6301", "size": 137}, {"name": "\u7db2\u8def", "size": 110}, {"name": "\u4e00\u500b", "size": 1037}, {"name": "\u8a18\u8005", "size": 427}, {"name": "\u4ed6\u5011", "size": 822}, {"name": "\u60f3\u8981", "size": 120}, {"name": "\u9023\u7d50", "size": 230}, {"name": "\u5e38\u5e38", "size": 105}, {"name": "\u5e02\u5834", "size": 113}, {"name": "\u59d4\u54e1\u6703", "size": 118}, {"name": "\u7576\u521d", "size": 101}, {"name": "\u9109\u6c11", "size": 186}, {"name": "\u4f3c\u4e4e", "size": 109}, {"name": "\u624b\u6a5f", "size": 144}, {"name": "\u9084\u6709", "size": 507}, {"name": "\u5f71\u7247", "size": 101}, {"name": "\u544a\u8a34", "size": 102}, {"name": "\u8655\u7406", "size": 135}, {"name": "\u76f8\u95dc", "size": 187}, {"name": "\u5b9a\u8981", "size": 102}, {"name": "\u672c\u4eba", "size": 109}, {"name": "\u672c\u4f86", "size": 154}, {"name": "\u8868\u793a", "size": 457}, {"name": "\u662f\u5426", "size": 113}, {"name": "\u600e\u9ebc", "size": 397}, {"name": "\u7576\u7136", "size": 276}, {"name": "\u4e0d\u8981", "size": 376}, {"name": "\u5f8c\u4f86", "size": 399}, {"name": "\u4f86\u6e90", "size": 197}, {"name": "\u7576\u6642", "size": 337}, {"name": "\u6574\u500b", "size": 112}, {"name": "\u9032\u884c", "size": 164}, {"name": "\u4e4b\u985e", "size": 109}, {"name": "\u6c7a\u5b9a", "size": 123}, {"name": "\u65bc\u662f", "size": 123}, {"name": "\u8a72\u662f", "size": 132}, {"name": "\u898f\u5b9a", "size": 108}, {"name": "\u6c92\u6709", "size": 1011}, {"name": "\u4ea4\u901a", "size": 106}, {"name": "\u4f86\u8aaa", "size": 114}, {"name": "\u56b4\u91cd", "size": 114}, {"name": "\u5e02\u9577", "size": 145}, {"name": "\u6bd4\u8f03", "size": 424}, {"name": "\u600e\u6a23", "size": 125}, {"name": "\u96d6\u7136", "size": 270}, {"name": "\u81ea\u7531", "size": 130}, {"name": "\u653f\u5e9c", "size": 300}, {"name": "\u5e02\u5e9c", "size": 106}, {"name": "\u8a18\u5f97", "size": 115}, {"name": "\u7a81\u7136", "size": 131}, {"name": "\u50cf\u662f", "size": 141}, {"name": "\u6a5f\u6703", "size": 136}, {"name": "\u653f\u6cbb", "size": 193}, {"name": "\u4eca\u5929", "size": 343}, {"name": "\u6c34\u6876", "size": 143}, {"name": "\u5f71\u97ff", "size": 196}, {"name": "\u751f\u6d3b", "size": 122}, {"name": "\u4eca\u5e74", "size": 122}, {"name": "\u540c\u5b78", "size": 164}, {"name": "\u81ea\u5df1", "size": 930}, {"name": "\u4e4b\u524d", "size": 296}, {"name": "\u4e4b\u5f8c", "size": 342}, {"name": "\u67ef\u6587", "size": 108}, {"name": "\u63a5\u53d7", "size": 119}, {"name": "\u975e\u5e38", "size": 246}, {"name": "\u65e5\u672c", "size": 411}, {"name": "\u9084\u662f", "size": 770}, {"name": "\u5169\u500b", "size": 194}, {"name": "\u4eba\u6c11", "size": 107}, {"name": "\u90a3\u9ebc", "size": 243}, {"name": "\u53d7\u5230", "size": 103}, {"name": "\u7e3d\u7d71", "size": 251}, {"name": "\u5c31\u662f", "size": 1285}, {"name": "\u6d3b\u52d5", "size": 134}, {"name": "\u90a3\u908a", "size": 104}, {"name": "\u6709\u9ede", "size": 167}, {"name": "\u7db2\u7ad9", "size": 104}, {"name": "\u5df2\u7d93", "size": 438}, {"name": "\u5c31\u7b97", "size": 117}, {"name": "\u76f8\u4fe1", "size": 140}, {"name": "\u8001\u5e2b", "size": 222}, {"name": "\u8001\u5a46", "size": 102}, {"name": "\u59b9\u59b9", "size": 179}, {"name": "\u958b\u59cb", "size": 432}, {"name": "\u9084\u8981", "size": 130}, {"name": "\u89ba\u5f97", "size": 578}, {"name": "\u6771\u897f", "size": 259}, {"name": "\u4eba\u54e1", "size": 146}, {"name": "\u7db2\u5740", "size": 198}, {"name": "\u7db2\u53cb", "size": 168}, {"name": "\u4e00\u8d77", "size": 261}, {"name": "\u56e0\u6b64", "size": 193}, {"name": "\u4e00\u822c", "size": 137}, {"name": "\u672a\u4f86", "size": 132}, {"name": "\u91ab\u5e2b", "size": 126}, {"name": "\u6642\u4ee3", "size": 123}, {"name": "\u7d93\u904e", "size": 101}, {"name": "\u66fe\u7d93", "size": 102}, {"name": "\u4eba\u5bb6", "size": 133}, {"name": "\u6642\u5019", "size": 525}, {"name": "\u4e00\u9ede", "size": 219}, {"name": "\u5e74\u6708\u65e5", "size": 113}, {"name": "\u53ea\u80fd", "size": 155}, {"name": "\u53ea\u8981", "size": 177}, {"name": "\u7acb\u59d4", "size": 179}]}